ruuvi_decoders/__init__.py
ruuvi_decoders/df3_decoder.py
ruuvi_decoders/df5_decoder.py
ruuvi_decoders/url_decoder.py
ruuvi_decoders-0.2.0.dist-info/AUTHORS.rst
ruuvi_decoders-0.2.0.dist-info/LICENSE
ruuvi_decoders-0.2.0.dist-info/METADATA
ruuvi_decoders-0.2.0.dist-info/WHEEL
ruuvi_decoders-0.2.0.dist-info/top_level.txt
ruuvi_decoders-0.2.0.dist-info/RECORD
