Metadata-Version: 2.1
Name: ruuvi-decoders
Version: 0.2.0
Summary: Decoders for raw ruuvi tag data payloads
Home-page: https://github.com/sergioisidoro/ruuvi_decoders
Author: Sergio Isidoro
Author-email: smaisidoro@gmail.com
License: MIT license
Keywords: ruuvi_decoders
Platform: UNKNOWN
Classifier: Development Status :: 2 - Pre-Alpha
Classifier: Intended Audience :: Developers
Classifier: License :: OSI Approved :: MIT License
Classifier: Natural Language :: English
Classifier: Programming Language :: Python :: 3
Classifier: Programming Language :: Python :: 3.5
Classifier: Programming Language :: Python :: 3.6
Classifier: Programming Language :: Python :: 3.7
Classifier: Programming Language :: Python :: 3.8
Classifier: Programming Language :: Python :: 3.9
Requires-Python: >=3.5
